write_composition.py
write_composition-1.7.4.data/data/Lib/site-packages/wc_data/bullshit_pasj.json
write_composition-1.7.4.data/data/Lib/site-packages/wc_data/data.json
write_composition-1.7.4.data/data/Lib/site-packages/wc_data/data_mingyan.json
write_composition-1.7.4.dist-info/METADATA
write_composition-1.7.4.dist-info/WHEEL
write_composition-1.7.4.dist-info/top_level.txt
write_composition-1.7.4.dist-info/RECORD
