Metadata-Version: 2.1
Name: write-composition
Version: 1.7.4
Summary: 手把手教你如何写出一篇完美的废话文章.
Home-page: UNKNOWN
Author: pythonnlgs
License: UNKNOWN
Platform: UNKNOWN
